cev/__init__.py
cev/_cli.py
cev/_compare.py
cev/_compare_metric_dropdown.py
cev/_compare_selection_type_dropdown.py
cev/_compare_zoom_toggle.py
cev/_embedding.py
cev/_embedding_comparison_widget.py
cev/_embedding_widget.py
cev/_version.py
cev/_widget_utils.py
cev/metrics.py
cev/widgets.py
cev/components/__init__.py
cev/components/_html_widget.py
cev/components/_marker_composition_logo.py
cev/components/_marker_selection_indicator.py
cev/components/_width_optimizer.py
cev-0.2.2.dist-info/METADATA
cev-0.2.2.dist-info/WHEEL
cev-0.2.2.dist-info/entry_points.txt
cev-0.2.2.dist-info/licenses/LICENSE
cev-0.2.2.dist-info/RECORD
