Metadata-Version: 2.3
Name: cev
Version: 0.2.2
Summary: comparative embedding visualization
Project-URL: homepage, https://github.com/OzetteTech/comparative-embedding-visualization
Author: Trevor Manz, Fritz Lekschas
License: Apache-2.0
License-File: LICENSE
Classifier: Intended Audience :: Developers
Classifier: Programming Language :: Python :: 3
Classifier: Programming Language :: Python :: 3.8
Classifier: Programming Language :: Python :: 3.9
Classifier: Programming Language :: Python :: 3.10
Classifier: Programming Language :: Python :: 3.11
Requires-Python: <3.12,>=3.8
Requires-Dist: anywidget>=0.2.3
Requires-Dist: cev-metrics>=0.1.2
Requires-Dist: ipywidgets>=8.0.0
Requires-Dist: jinja2>=3.0.0
Requires-Dist: jupyter-scatter>=0.14.0
Requires-Dist: numpy<2.0,>=1.0
Requires-Dist: pandas<2.0,>=1.0
Requires-Dist: pooch>=1.3.0
Requires-Dist: pyarrow
Provides-Extra: dev
Requires-Dist: black[jupyter]==23.1.0; extra == 'dev'
Requires-Dist: jupyterlab; extra == 'dev'
Requires-Dist: pytest; extra == 'dev'
Requires-Dist: ruff==0.0.246; extra == 'dev'
Provides-Extra: notebooks
Requires-Dist: fastparquet; extra == 'notebooks'
Requires-Dist: matplotlib; extra == 'notebooks'
Requires-Dist: pyarrow; extra == 'notebooks'
